{
    "title": "VonZipper : Taj Burrow in the Cletus",
    "description": "Whittled on the front porch in the spirit of \"don't let the man do to you what he done to me.\" The Cletus was born under the seventh sun. Pull out your black cat bone and get your mojo working in this honeydripper.",
    "referenceId": null,
    "date_created": "1401377711",
    "date_modified": "1445879201",
    "tags": "",
    "sourceId": "4",
    "VIDEO_LENGTH": "SHORT",
    "status": "approved",
    "visibility": "1",
    "video_brand": null,
    "video_celeb": null,
    "video_activity": null,
    "VV_VI": null,
    "CVV_VI": null,
    "engagement_score": null,
    "conversion_score": null,
    "id": "170476",
    "loginId": "753",
    "entityType": "1",
    "titleTextEncoded": "VonZipper-Taj-Burrow-in-the-Cletus",
    "category": null,
    "duration": "21",
    "settings": [],
    "asset": {
        "author": "VonZipper",
        "hdvFlag": 1,
        "hookText": "Whittled on the front porch in the spirit of \"don't let the man do to you what he done to me.\" The Cletus was born under the seventh sun. Pull out your black...",
        "tags": "",
        "thumbnailUrl": "https:\/\/i.ytimg.com\/vi\/491BWRTLxrE\/sddefault.jpg",
        "uploadDate": 1326835602,
        "videoId": "491BWRTLxrE",
        "mediaDuration": "21",
        "prettyDuration": "00:00:21"
    },
    "transcripts": null,
    "metrics_statistics": null,
    "tvp_concept": null,
    "tvp_entity_company": null,
    "tvp_entity_facility": null,
    "tvp_entity_geographicfeature": null,
    "tvp_entity_healthcondition": null,
    "tvp_entity_location": null,
    "tvp_entity_movie": null,
    "tvp_entity_musicgroup": null,
    "tvp_entity_organization": null,
    "tvp_entity_person": null,
    "tvp_entity_sport": null,
    "tvp_entity_sportingevent": null,
    "tvp_entity_televisionshow": null,
    "tvp_entity_twitterhandle": null,
    "tvp_entity_vehicle": null,
    "tvp_category_1": null,
    "tvp_category_2": null,
    "tvp_category_3": null,
    "tvp_category_4": null,
    "tvp_category_5": null,
    "tvp_profiles": null
}